extend_mt19937_predictor.py
extend_mt19937_predictor-19937.0.3.dist-info/LICENSE
extend_mt19937_predictor-19937.0.3.dist-info/METADATA
extend_mt19937_predictor-19937.0.3.dist-info/WHEEL
extend_mt19937_predictor-19937.0.3.dist-info/top_level.txt
extend_mt19937_predictor-19937.0.3.dist-info/RECORD
