Metadata-Version: 2.1
Name: extend-mt19937-predictor
Version: 19937.0.3
Summary: Extend Mt19937 Predictor
Home-page: https://github.com/NonupleBroken/ExtendMT19937Predictor
Author: NonupleBroken
Author-email: nonuplebroken@gmail.com
License: GPLv3
Classifier: Development Status :: 5 - Production/Stable
Classifier: Intended Audience :: Developers
Classifier: License :: OSI Approved :: GNU General Public License v3 (GPLv3)
Classifier: Operating System :: Microsoft :: Windows
Classifier: Operating System :: MacOS
Classifier: Operating System :: Unix
Classifier: Programming Language :: Python :: 2
Classifier: Programming Language :: Python :: 3
Classifier: Topic :: Security :: Cryptography
License-File: LICENSE
